Metadata-Version: 2.1
Name: autosynthesis
Version: 0.0.31
Summary: A toolkit for automated synthesis of biorefinery processes including pretreatment, conversion, separation, and upgrading.
Home-page: https://github.com/sarangbhagwat/autosynthesis
Download-URL: https://github.com/sarangbhagwat/autosynthesis.git
Author: Sarang S. Bhagwat
Author-email: sarangbhagwat.developer@gmail.com
License: MIT
Platform: Windows
Platform: Mac
Platform: Linux
Classifier: Development Status :: 3 - Alpha
Classifier: Intended Audience :: Science/Research
Classifier: License :: OSI Approved :: MIT License
Classifier: Operating System :: MacOS
Classifier: Operating System :: Microsoft :: Windows
Classifier: Operating System :: POSIX
Classifier: Operating System :: POSIX :: BSD
Classifier: Operating System :: POSIX :: Linux
Classifier: Operating System :: Unix
Classifier: Programming Language :: Python :: 3.9
Requires-Python: >=3.9
License-File: LICENSE
Requires-Dist: biosteam>=2.33.2
Requires-Dist: xlsxwriter
